moat/db/label/__init__.py
moat/db/label/_cfg.yaml
moat/db/label/_main.py
moat/db/label/model.py
moat/db/label/model_.py
moat/db/label/pdf.py
moat/label/__init__.py
moat/label/_cfg.yaml
moat/label/_main.py
moat/label/model.py
moat/label/model_.py
moat/label/pdf.py
moat_db_label-0.0.2.dist-info/licenses/LICENSE.txt
moat_db_label-0.0.2.dist-info/METADATA
moat_db_label-0.0.2.dist-info/WHEEL
moat_db_label-0.0.2.dist-info/top_level.txt
moat_db_label-0.0.2.dist-info/RECORD
