Metadata-Version: 2.4
Name: moat-db-label
Version: 0.0.2
Summary: MoaT support for printing labels
Author-email: Matthias Urlichs <matthias@urlichs.de>
Project-URL: homepage, https://m-o-a-t.org
Project-URL: repository, https://github.com/M-o-a-T/moat
Keywords: MoaT
Classifier: Intended Audience :: Developers
Classifier: Programming Language :: Python :: 3
Classifier: Framework :: AsyncIO
Classifier: Framework :: Trio
Classifier: Framework :: AnyIO
Classifier: Development Status :: 4 - Beta
Requires-Python: >=3.8
License-File: LICENSE.txt
Requires-Dist: moat-util~=0.61.1
Requires-Dist: moat-db~=0.2.5
Requires-Dist: moat-lib-config~=0.1.0
Requires-Dist: moat-lib-run~=0.1.0
Provides-Extra: event
Requires-Dist: attr; extra == "event"
Requires-Dist: outcome; extra == "event"
Provides-Extra: main
Requires-Dist: asyncclick; extra == "main"
Requires-Dist: getpass; extra == "main"
Provides-Extra: msg
Requires-Dist: msgpack; extra == "msg"
Provides-Extra: path
Requires-Dist: simpleeval; extra == "path"
Provides-Extra: queue
Requires-Dist: outcome; extra == "queue"
Provides-Extra: systemd
Requires-Dist: systemd.daemon; extra == "systemd"
Provides-Extra: yaml
Requires-Dist: ruyaml; extra == "yaml"
Provides-Extra: time
Requires-Dist: calendar; extra == "time"
Provides-Extra: dev
Requires-Dist: flake8; extra == "dev"
Requires-Dist: isort; extra == "dev"
Dynamic: license-file
